{
	"name": "Incremental",
	"properties": {
		"activities": [
			{
				"name": "Water_Mark",
				"type": "Lookup",
				"dependsOn": [],
				"policy": {
					"timeout": "0.12:00:00",
					"retry": 0,
					"retryIntervalInSeconds": 30,
					"secureOutput": false,
					"secureInput": false
				},
				"userProperties": [],
				"typeProperties": {
					"source": {
						"type": "AzureSqlSource",
						"queryTimeout": "02:00:00",
						"partitionOption": "None"
					},
					"dataset": {
						"referenceName": "ds_azsql_inc",
						"type": "DatasetReference",
						"parameters": {
							"table_name": "water_mark",
							"schema_name": "emp"
						}
					},
					"firstRowOnly": false
				}
			},
			{
				"name": "ForEach1",
				"type": "ForEach",
				"dependsOn": [
					{
						"activity": "Water_Mark",
						"dependencyConditions": [
							"Succeeded"
						]
					}
				],
				"userProperties": [],
				"typeProperties": {
					"items": {
						"value": "@activity('Water_Mark').output.value",
						"type": "Expression"
					},
					"isSequential": false,
					"activities": [
						{
							"name": "Max_Value",
							"type": "Lookup",
							"dependsOn": [],
							"policy": {
								"timeout": "0.12:00:00",
								"retry": 0,
								"retryIntervalInSeconds": 30,
								"secureOutput": false,
								"secureInput": false
							},
							"userProperties": [],
							"typeProperties": {
								"source": {
									"type": "AzureSqlSource",
									"sqlReaderQuery": {
										"value": "select max(@{item().delta_col}) as max_value from @{item().table_schema}.@{item().table_name}",
										"type": "Expression"
									},
									"queryTimeout": "02:00:00",
									"partitionOption": "None"
								},
								"dataset": {
									"referenceName": "ds_azsql_inc",
									"type": "DatasetReference",
									"parameters": {
										"table_name": "''",
										"schema_name": "''"
									}
								}
							}
						},
						{
							"name": "Copy data1",
							"type": "Copy",
							"dependsOn": [
								{
									"activity": "Max_Value",
									"dependencyConditions": [
										"Succeeded"
									]
								}
							],
							"policy": {
								"timeout": "0.12:00:00",
								"retry": 0,
								"retryIntervalInSeconds": 30,
								"secureOutput": false,
								"secureInput": false
							},
							"userProperties": [],
							"typeProperties": {
								"source": {
									"type": "AzureSqlSource",
									"sqlReaderQuery": {
										"value": "select * from @{item().table_schema}.@{item().table_name}\nwhere @{item().delta_col} > '@{item().last_loaded_date}'",
										"type": "Expression"
									},
									"queryTimeout": "02:00:00",
									"partitionOption": "None"
								},
								"sink": {
									"type": "DelimitedTextSink",
									"storeSettings": {
										"type": "AzureBlobFSWriteSettings"
									},
									"formatSettings": {
										"type": "DelimitedTextWriteSettings",
										"quoteAllText": true,
										"fileExtension": ".csv"
									}
								},
								"enableStaging": false,
								"translator": {
									"type": "TabularTranslator",
									"typeConversion": true,
									"typeConversionSettings": {
										"allowDataTruncation": true,
										"treatBooleanAsNumber": false
									}
								}
							},
							"inputs": [
								{
									"referenceName": "ds_azsql_inc",
									"type": "DatasetReference",
									"parameters": {
										"table_name": "''",
										"schema_name": "''"
									}
								}
							],
							"outputs": [
								{
									"referenceName": "az_adlsgen2",
									"type": "DatasetReference",
									"parameters": {
										"folder_name": {
											"value": "@concat(item().folder_name,formatDateTime(utcNow(), 'yyyy/MM/dd hh/mm/ss'))",
											"type": "Expression"
										},
										"file_name": {
											"value": "@concat(item().table_name,'.csv')",
											"type": "Expression"
										}
									}
								}
							]
						},
						{
							"name": "Update_Wark_Mark",
							"type": "SqlServerStoredProcedure",
							"dependsOn": [
								{
									"activity": "Copy data1",
									"dependencyConditions": [
										"Succeeded"
									]
								}
							],
							"policy": {
								"timeout": "0.12:00:00",
								"retry": 0,
								"retryIntervalInSeconds": 30,
								"secureOutput": false,
								"secureInput": false
							},
							"userProperties": [],
							"typeProperties": {
								"storedProcedureName": "[dbo].[usp_watermark_update]",
								"storedProcedureParameters": {
									"last_loaded_value": {
										"value": {
											"value": "@activity('Max_Value').output.firstRow.max_value",
											"type": "Expression"
										},
										"type": "String"
									},
									"table_name": {
										"value": {
											"value": "@item().table_name",
											"type": "Expression"
										},
										"type": "String"
									}
								}
							},
							"linkedServiceName": {
								"referenceName": "ds_azsql_inc",
								"type": "LinkedServiceReference"
							}
						}
					]
				}
			}
		],
		"annotations": [],
		"lastPublishTime": "2026-05-30T04:09:07Z"
	},
	"type": "Microsoft.DataFactory/factories/pipelines"
}